lumbermill/BaseModule.py
lumbermill/BaseMultiProcessModule.py
lumbermill/BaseThreadedModule.py
lumbermill/LumberMill.py
lumbermill/__init__.py
lumbermill/constants.py
lumbermill/test.py
lumbermill/assets/ip_protocols
lumbermill/assets/grok_patterns/firewalls
lumbermill/assets/grok_patterns/grok-patterns
lumbermill/assets/grok_patterns/haproxy
lumbermill/assets/grok_patterns/php
lumbermill/assets/maxmind/GeoLite2-ASN.mmdb
lumbermill/assets/maxmind/GeoLite2-City.mmdb
lumbermill/assets/maxmind/LICENSE
lumbermill/assets/webserver_docroot/static/css/bootstrap-theme.min.css
lumbermill/assets/webserver_docroot/static/css/bootstrap.min.css
lumbermill/assets/webserver_docroot/static/css/gambolputty_web.css
lumbermill/assets/webserver_docroot/static/fonts/glyphicons-halflings-regular.eot
lumbermill/assets/webserver_docroot/static/fonts/glyphicons-halflings-regular.svg
lumbermill/assets/webserver_docroot/static/fonts/glyphicons-halflings-regular.ttf
lumbermill/assets/webserver_docroot/static/fonts/glyphicons-halflings-regular.woff
lumbermill/assets/webserver_docroot/static/fonts/glyphicons-halflings-regular.woff2
lumbermill/assets/webserver_docroot/static/js/bootstrap.min.js
lumbermill/assets/webserver_docroot/static/js/config.js
lumbermill/assets/webserver_docroot/static/js/gambolputty_web.js
lumbermill/assets/webserver_docroot/static/js/jquery.min.js
lumbermill/assets/webserver_docroot/static/js/utils.js
lumbermill/assets/webserver_docroot/templates/index.html
lumbermill/assets/webserver_docroot/templates/server_configuration.html
lumbermill/assets/webserver_docroot/templates/server_configuration_text.html
lumbermill/assets/webserver_docroot/templates/server_info.html
lumbermill/assets/webserver_docroot/templates/server_log.html
lumbermill/cluster/Pack.py
lumbermill/cluster/PackConfiguration.py
lumbermill/cluster/__init__.py
lumbermill/input/Beats.py
lumbermill/input/ElasticSearch.py
lumbermill/input/File.py
lumbermill/input/Kafka.py
lumbermill/input/NmapScanner.py
LumberMill-0.9.5.7.dist-info/LICENSE
LumberMill-0.9.5.7.dist-info/METADATA
LumberMill-0.9.5.7.dist-info/WHEEL
LumberMill-0.9.5.7.dist-info/entry_points.txt
LumberMill-0.9.5.7.dist-info/top_level.txt
LumberMill-0.9.5.7.dist-info/RECORD
