Metadata-Version: 2.1
Name: LumberMill
Version: 0.9.5.7
Summary: A logparser with module support.
Home-page: https://github.com/dstore-dbap/LumberMill/
Author: Björn Puttmann
Author-email: nospam@poitin.de
License: LICENSE
Classifier: Intended Audience :: System Administrators
Classifier: License :: OSI Approved :: Apache Software License
Classifier: Programming Language :: Python :: 2.7
Classifier: Programming Language :: Python :: Implementation :: PyPy
Classifier: Topic :: System :: Logging
License-File: LICENSE
Requires-Dist: crypto (>=1.0.0)
Requires-Dist: pylru (>=1.0.0)
Requires-Dist: PyYAML (>=2.0.0)
Requires-Dist: redis (>=1.0.0)
Requires-Dist: hiredis (>=0.1.0)
Requires-Dist: simplekv (>=0.5.0)
Requires-Dist: tornado (<=5.1.0)
Requires-Dist: pyzmq (>=10.0.0)
Requires-Dist: psutil
Requires-Dist: bs4
Requires-Dist: elasticsearch (>=2.1.0)
Requires-Dist: mmh3 (>=2.0.0)
Requires-Dist: msgpack-python (>=0.4.0)
Requires-Dist: geoip2 (>=2.3.0)
Requires-Dist: ua-parser (>=0.5.0)
Requires-Dist: kafka-python (>=0.8.0)
Requires-Dist: dnspython (>=1.0.0)
Requires-Dist: tld (>=0.5.0)
Requires-Dist: pymongo (>=3.0.0)
Requires-Dist: glob2 (>=0.3)
Requires-Dist: pytz
Requires-Dist: py-zabbix (>=1.1.1)
Requires-Dist: Pygments (>=2.0.0)
Requires-Dist: nest-asyncio
